[{"_id":"64783762286c8688e07c26f1","userId":"64783762286c8688e07c26ef","notifications":[],"createdAt":"2023-06-01T06:14:58.429Z","updatedAt":"2023-06-01T06:14:58.429Z","__v":0},{"_id":"64788dfd295e2f184e55d211","userId":"64788dfd295e2f184e55d20f","notifications":[{"title":"title","message":"message","dateSent":"2023-06-03T05:15:28.961Z","category":"category","isRead":true,"_id":"647acc703096c79f8a15fadc"},{"title":"title","message":"message","dateSent":"2023-06-05T05:57:50.346Z","category":"category","isRead":true,"_id":"647d795e4bac5b6e7cd9e1f2"},{"title":"title","message":"message","dateSent":"2023-06-05T06:07:29.353Z","category":"category","isRead":true,"_id":"647d7ba1cb37a00e38a94e43"},{"title":"title","message":"message","dateSent":"2023-06-07T10:11:17.507Z","category":"category","isRead":true,"_id":"648057c59c5bcb2cede2e6ee"},{"title":"title","message":"message","dateSent":"2023-06-07T10:11:22.194Z","category":"category","isRead":true,"_id":"648057ca9c5bcb2cede2e6fd"},{"title":"title","message":"message","dateSent":"2023-06-09T08:30:58.203Z","category":"category","isRead":true,"_id":"6482e342c2e6b952e2bf8d5d"},{"title":"title","message":"message","dateSent":"2023-06-09T08:51:38.004Z","category":"category","isRead":true,"_id":"6482e81a451740545054cb9a"},{"title":"title","message":"message","dateSent":"2023-06-09T08:52:43.652Z","category":"category","isRead":true,"_id":"6482e85b01c8527a1e433155"},{"title":"title","message":"message","dateSent":"2023-06-09T08:53:54.824Z","category":"category","isRead":true,"_id":"6482e8a292dd724bd5441419"},{"title":"title","message":"message","dateSent":"2023-06-26T17:19:29.840Z","category":"category","isRead":true,"_id":"6499c8a1b053c96132889855"},{"title":"title","message":"message","dateSent":"2023-06-26T17:37:21.889Z","category":"category","isRead":true,"_id":"6499ccd17ae444dfd859a134"},{"title":"title","message":"message","dateSent":"2023-06-26T17:37:52.448Z","category":"category","isRead":true,"_id":"6499ccf07ae444dfd859a152"},{"title":"title","message":"message","dateSent":"2023-06-26T17:38:11.197Z","category":"category","isRead":true,"_id":"6499cd037ae444dfd859a162"},{"title":"c","message":"","dateSent":"2023-06-27T14:17:55.205Z","category":"error","isRead":true,"_id":"649aef93a9a8e9cdbcab65e4"}],"createdAt":"2023-06-01T12:24:29.308Z","updatedAt":"2023-06-27T14:18:56.502Z","__v":0},{"_id":"6478a2e190e054ed836f69f6","userId":"6478a2e090e054ed836f69f4","notifications":[],"createdAt":"2023-06-01T13:53:37.201Z","updatedAt":"2023-06-01T13:53:37.201Z","__v":0},{"_id":"6478a467c7fd97e8fb52e575","userId":"6478a467c7fd97e8fb52e573","notifications":[{"title":"title","message":"message","dateSent":"2023-06-19T16:21:07.425Z","category":"category","isRead":true,"_id":"6490807344f79dd9bfa27e54"},{"title":"title","message":"message","dateSent":"2023-06-20T01:33:36.786Z","category":"category","isRead":true,"_id":"649101f0be1c368d1d176b5a"}],"createdAt":"2023-06-01T14:00:07.398Z","updatedAt":"2023-06-20T01:43:31.388Z","__v":0},{"_id":"647ff607402b8d9ff09e5cde","userId":"647ff607402b8d9ff09e5cdc","notifications":[{"title":"title","message":"message","dateSent":"2023-06-20T02:09:38.058Z","category":"category","isRead":false,"_id":"64910a623b5e2d9c71d1cca1"},{"title":"title","message":"message","dateSent":"2023-06-26T17:18:54.725Z","category":"category","isRead":false,"_id":"6499c87eb053c9613288983e"}],"createdAt":"2023-06-07T03:14:15.467Z","updatedAt":"2023-06-26T17:18:54.726Z","__v":0},{"_id":"647ff6f4402b8d9ff09e5ce9","userId":"647ff6f4402b8d9ff09e5ce7","notifications":[],"createdAt":"2023-06-07T03:18:12.868Z","updatedAt":"2023-06-07T03:18:12.868Z","__v":0},{"_id":"647ff861402b8d9ff09e5cf2","userId":"647ff860402b8d9ff09e5cf0","notifications":[],"createdAt":"2023-06-07T03:24:17.013Z","updatedAt":"2023-06-07T03:31:03.758Z","__v":0},{"_id":"64803eeec3251fd9714c2fa4","userId":"64803eeec3251fd9714c2fa2","notifications":[],"createdAt":"2023-06-07T08:25:18.942Z","updatedAt":"2023-06-07T08:25:18.942Z","__v":0},{"_id":"6480600fbb20c9a92549c8c2","userId":"6480600fbb20c9a92549c8c0","notifications":[],"createdAt":"2023-06-07T10:46:39.894Z","updatedAt":"2023-06-07T10:46:39.894Z","__v":0},{"_id":"648060a77312728670b955d3","userId":"648060a67312728670b955d1","notifications":[],"createdAt":"2023-06-07T10:49:11.030Z","updatedAt":"2023-06-07T10:49:11.030Z","__v":0},{"_id":"648070cf9a74896d21b7d496","userId":"648070cf9a74896d21b7d494","notifications":[],"createdAt":"2023-06-07T11:58:07.929Z","updatedAt":"2023-06-07T11:58:07.929Z","__v":0}]